{
  "cursos": [
    {
      "id": "1",
      "nome": "JavaScript",
      "descricao": "Aprenda JavaScript do básico ao intermediário, desde manipulação do DOM a requisições Fetch API, promises entre outras.",
      "cargaHoraria": 20,
      "preco": 300.50
    },
    {
      "id": "2",
      "nome": "CSS - Flexbox",
      "descricao": "Aprenda a criar layouts do zero utilizando CSS Flexbox, para criação de sites responsivos. No curso será ensinado as principais propriedades do Flexbox.",
      "cargaHoraria": 5,
      "preco": 150
    },
    {
      "id": "3",
      "nome": "CSS - Grid Layout",
      "descricao": "Aprenda a criar layouts complexos utilizando a nova especificação de CSS.",
      "cursosOpcionais": [
        {
          "id": "2"
        }
      ],
      "cargaHoraria": 5,
      "preco": 150
    },
    {
      "id": "4",
      "nome": "CSS - SCSS",
      "descricao": "Aprenda a utilizar o pré-processador SCSS de CSS para facilitar a sua vida no dia-a-dia.",
      "preRequisitos": [
        {
          "id": "2"
        },
        {
          "id": "3"
        }
      ],
      "cargaHoraria": 8,
      "preco": 250
    },
    {
      "id": "5",
      "nome": "Angular 2+",
      "descricao": "Aprenda a utilizar o framework Angular 2+ para criar SPA - Single Page Application. \\n Será ensinado desde o básico até o intermediário, no curso será utilizado o Material Design e outras libs para apresentação que podem ser usadas para facilitar o desenvolimento das aplicações no cotidiano.",
      "preRequisitos": [
        {
          "id": "1"
        }
      ],
      "cursosOpcionais": [
        {
          "id": "2"
        }
      ],
      "cargaHoraria": 25,
      "preco": 550.90
    }
  ]
}